resumex/__init__.py
resumex/job/__init__.py
resumex/job/job_graph.py
resumex/job/mp_executor.py
resumex/resume/__init__.py
resumex/resume/easy_jsonl.py
resumex/resume/retry.py
resumex-0.0.2.dist-info/METADATA
resumex-0.0.2.dist-info/WHEEL
resumex-0.0.2.dist-info/RECORD
