Metadata-Version: 2.1
Name: resumex
Version: 0.0.2
Summary: 
Author: Yikai Lai
Author-email: laiyk5@163.com
Requires-Python: >=3.11,<4.0
Classifier: Programming Language :: Python :: 3
Classifier: Programming Language :: Python :: 3.11
Classifier: Programming Language :: Python :: 3.12
Requires-Dist: graphviz (>=0.20.3,<0.21.0)
Requires-Dist: jsonlines (>=4.0.0,<5.0.0)
Requires-Dist: pydantic (>=2.8.2,<3.0.0)
